aioquic_pmd3/__init__.py
aioquic_pmd3/_buffer.py
aioquic_pmd3/_crypto.py
aioquic_pmd3/buffer.py
aioquic_pmd3/tls.py
aioquic_pmd3/asyncio/__init__.py
aioquic_pmd3/asyncio/client.py
aioquic_pmd3/asyncio/protocol.py
aioquic_pmd3/asyncio/server.py
aioquic_pmd3/h0/__init__.py
aioquic_pmd3/h0/connection.py
aioquic_pmd3/h3/__init__.py
aioquic_pmd3/h3/connection.py
aioquic_pmd3/h3/events.py
aioquic_pmd3/h3/exceptions.py
aioquic_pmd3/quic/__init__.py
aioquic_pmd3/quic/configuration.py
aioquic_pmd3/quic/connection.py
aioquic_pmd3/quic/crypto.py
aioquic_pmd3/quic/events.py
aioquic_pmd3/quic/logger.py
aioquic_pmd3/quic/packet.py
aioquic_pmd3/quic/packet_builder.py
aioquic_pmd3/quic/rangeset.py
aioquic_pmd3/quic/recovery.py
aioquic_pmd3/quic/retry.py
aioquic_pmd3/quic/stream.py
aioquic_pmd3-0.0.2.dist-info/LICENSE
aioquic_pmd3-0.0.2.dist-info/METADATA
aioquic_pmd3-0.0.2.dist-info/WHEEL
aioquic_pmd3-0.0.2.dist-info/top_level.txt
aioquic_pmd3-0.0.2.dist-info/RECORD
