Metadata-Version: 2.1
Name: aioquic-pmd3
Version: 0.0.2
Summary: An implementation of QUIC and HTTP/3
Author-email: doronz88 <doron88@gmail.com>
License: BSD-3-Clause
Project-URL: homepage, https://github.com/doronz88/aioquic-pmd3
Project-URL: documentation, https://aioquic.readthedocs.io/
Classifier: Development Status :: 4 - Beta
Classifier: Environment :: Web Environment
Classifier: Intended Audience :: Developers
Classifier: License :: OSI Approved :: BSD License
Classifier: Operating System :: OS Independent
Classifier: Programming Language :: Python
Classifier: Programming Language :: Python :: 3
Classifier: Programming Language :: Python :: 3.8
Classifier: Programming Language :: Python :: 3.9
Classifier: Programming Language :: Python :: 3.10
Classifier: Programming Language :: Python :: 3.11
Classifier: Topic :: Internet :: WWW/HTTP
Requires-Python: >=3.8
License-File: LICENSE
Requires-Dist: certifi
Requires-Dist: pylsqpack <0.4.0,>=0.3.3
Requires-Dist: pyopenssl >=22
Requires-Dist: service-identity >=23.1.0
Provides-Extra: dev
Requires-Dist: coverage[toml] >=7.2.2 ; extra == 'dev'
